servd/__init__.py
servd-1.0.0.dist-info/LICENSE
servd-1.0.0.dist-info/WHEEL
servd-1.0.0.dist-info/METADATA
servd-1.0.0.dist-info/RECORD
